{
  "resourceType": "Organization",
  "id": "examplehospital3-ehr2",
  "extension": [
    {
      "url": "http://hl7.org/fhir/smart-app-launch/StructureDefinition/patient-access-url",
      "valueUrl": "https://patientgateway.examplehospital1-ehr1.org"
    },
    {
      "url": "http://hl7.org/fhir/smart-app-launch/StructureDefinition/patient-access-description",
      "valueMarkdown": "Pediatrics Portal is a Web-based, easy-to-use, and secure way to access your child's information at your convenience."
    }
  ],
  "identifier": [
    {
      "system": "urn:ietf:rfc:3986",
      "value": "https://examplehospital3.org"
    }
  ],
  "active": true,
  "type": [
    {
      "coding": [
        {
          "system": "http://hl7.org/fhir/smart-app-launch/CodeSystem/patient-access-category",
          "code": "clinical",
          "display": "Clinical Care provider"
        }
      ]
    }
  ],
  "name": "ExampleHospital3",
  "alias": [
    "GoodCare Cancer Center"
  ],
  "telecom": [
    {
      "system": "url",
      "value": "https://www.example.org/examplehospital3/"
    }
  ],
  "address": [
    {
      "city": "Boston",
      "state": "MA"
    }
  ],
  "partOf": {
    "reference": "Organization/examplehospital2-ehr2"
  }
}
